training/__init__.py
training/training_model.py
transactify/__init__.py
transactify/find_my_txn_category.py
transactify/predict_category.py
transactify/transactify_model.pkl
transactify-0.1.1.dist-info/METADATA
transactify-0.1.1.dist-info/WHEEL
transactify-0.1.1.dist-info/top_level.txt
transactify-0.1.1.dist-info/RECORD
