Metadata-Version: 2.1
Name: transactify
Version: 0.1.1
Summary: A Python module for predicting transaction categorization
Home-page: https://github.com/web-slate/transactify
Author: Venkatraman.R
Author-email: ramsunvtech@gmail.com
License: MIT
Requires-Dist: scikit-learn
